kmprograms_calc/__init__.py
kmprograms_calc/action/__init__.py
kmprograms_calc/action/mul_action.py
kmprograms_calc/action/sub_action.py
kmprograms_calc/action/x_action.py
kmprograms_calc/operations.py
adamson123_kmprograms_calc-0.1.3.dist-info/METADATA
adamson123_kmprograms_calc-0.1.3.dist-info/WHEEL
adamson123_kmprograms_calc-0.1.3.dist-info/RECORD
