Metadata-Version: 2.4
Name: adamson123-kmprograms-calc
Version: 0.1.3
Summary: pierwszy proejkt poetry podczas naszej nauki
Author: adam
Author-email: adame@k.com
Requires-Python: >=3.12
Classifier: Programming Language :: Python :: 3
Classifier: Programming Language :: Python :: 3.12
Classifier: Programming Language :: Python :: 3.13
Classifier: Programming Language :: Python :: 3.14
Requires-Dist: pytz (>=2025.2,<2026.0)
